mkdocs_unused_files/__init__.py
mkdocs_unused_files/plugin.py
mkdocs_unused_files-0.2.0.dist-info/LICENSE
mkdocs_unused_files-0.2.0.dist-info/METADATA
mkdocs_unused_files-0.2.0.dist-info/WHEEL
mkdocs_unused_files-0.2.0.dist-info/entry_points.txt
mkdocs_unused_files-0.2.0.dist-info/top_level.txt
mkdocs_unused_files-0.2.0.dist-info/RECORD
