Metadata-Version: 2.1
Name: mkdocs-unused-files
Version: 0.2.0
Summary: An MkDocs plugin to find unused (orphaned) files in your project.
Home-page: https://github.com/wilhelmer/mkdocs-unused-files.git
Author: Lars Wilhelmer
Author-email: lars@wilhelmer.de
License: MIT
Keywords: mkdocs
Classifier: Development Status :: 4 - Beta
Classifier: Intended Audience :: Developers
Classifier: Intended Audience :: Information Technology
Classifier: License :: OSI Approved :: MIT License
Classifier: Programming Language :: Python
Classifier: Programming Language :: Python :: 3 :: Only
Classifier: Programming Language :: Python :: 3.4
Classifier: Programming Language :: Python :: 3.5
Classifier: Programming Language :: Python :: 3.6
Classifier: Programming Language :: Python :: 3.7
Requires-Python: >=2.7
License-File: LICENSE
Requires-Dist: mkdocs (>=1.0.4)
Requires-Dist: beautifulsoup4 (>=4.12.0)
